MANIFEST.in
README.rst
setup.py
django_commons/__init__.py
django_commons/apps.py
django_commons/context_processors.py
django_commons/fields.py
django_commons/logging.py
django_commons/managers.py
django_commons/models.py
django_commons/password_validation.py
django_commons/receivers.py
django_commons/serialization.py
django_commons/tests.py
django_commons/validators.py
django_commons/views.py
django_commons.egg-info/PKG-INFO
django_commons.egg-info/SOURCES.txt
django_commons.egg-info/dependency_links.txt
django_commons.egg-info/not-zip-safe
django_commons.egg-info/requires.txt
django_commons.egg-info/top_level.txt
django_commons/admin/__init__.py
django_commons/admin/admin.py
django_commons/admin/list_filters.py
django_commons/management/__init__.py
django_commons/management/commands/__init__.py
django_commons/management/commands/createusers.py
django_commons/management/commands/htmlstats.py
django_commons/middleware/__init__.py
django_commons/middleware/cache.py
django_commons/middleware/csrf.py
django_commons/middleware/lang.py
django_commons/middleware/thread_locals.py
django_commons/middleware/timezone.py
django_commons/migrations/__init__.py